odoo/addons/l10n_jp_country_state/README.rst
odoo/addons/l10n_jp_country_state/__init__.py
odoo/addons/l10n_jp_country_state/__manifest__.py
odoo/addons/l10n_jp_country_state/data/res_country_state.xml
odoo/addons/l10n_jp_country_state/i18n/ja.po
odoo/addons/l10n_jp_country_state/static/description/icon.png
odoo11_addon_l10n_jp_country_state-11.0.1.0.0.dist-info/DESCRIPTION.rst
odoo11_addon_l10n_jp_country_state-11.0.1.0.0.dist-info/METADATA
odoo11_addon_l10n_jp_country_state-11.0.1.0.0.dist-info/RECORD
odoo11_addon_l10n_jp_country_state-11.0.1.0.0.dist-info/WHEEL
odoo11_addon_l10n_jp_country_state-11.0.1.0.0.dist-info/metadata.json
odoo11_addon_l10n_jp_country_state-11.0.1.0.0.dist-info/top_level.txt
